sweetiepy/__init__.py
sweetiepy/connection/__init__.py
sweetiepy/connection/mongodb.py
sweetiepy/data/__init__.py
sweetiepy/data/cgm.py
sweetiepy/data/merged.py
sweetiepy/data/pump.py
sweetiepy/utils/__init__.py
sweetiepy/utils/debug.py
sweetiepy-1.0.1.dist-info/METADATA
sweetiepy-1.0.1.dist-info/WHEEL
sweetiepy-1.0.1.dist-info/RECORD
