Metadata-Version: 2.4
Name: sweetiepy
Version: 1.0.1
Summary: Type 1 Diabetes Data Analysis from DIY Loop system
Author-email: Michelle Weirathmueller <info@waveformanalytics.com>
License-Expression: MIT
Requires-Python: >=3.12
Requires-Dist: marimo>=0.14.11
Requires-Dist: matplotlib>=3.10.3
Requires-Dist: pandas-stubs==2.3.0.250703
Requires-Dist: pandas>=2.3.1
Requires-Dist: plotly>=6.2.0
Requires-Dist: pyarrow>=20.0.0
Requires-Dist: pymongo>=4.13.2
Requires-Dist: python-dateutil>=2.9.0.post0
Requires-Dist: python-dotenv>=1.1.1
Requires-Dist: pytz>=2024.1
Provides-Extra: dev
Requires-Dist: pytest>=8.0.0; extra == 'dev'
Requires-Dist: ruff>=0.1.0; extra == 'dev'
Requires-Dist: twine>=6.1.0; extra == 'dev'
